<keymap version="1" name="Mac OS X copy" parent="Mac OS X">
  <action id="EmmetEverywhere">
    <keyboard-shortcut first-keystroke="alt tab" />
  </action>
  <action id="FileChooser.TogglePathShowing" />
  <action id="GotoFile">
    <keyboard-shortcut first-keystroke="meta p" />
  </action>
  <action id="NextSplitter" />
  <action id="NextTab">
    <keyboard-shortcut first-keystroke="ctrl page_down" />
  </action>
  <action id="ParameterInfo" />
  <action id="PreviousTab">
    <keyboard-shortcut first-keystroke="ctrl page_up" />
  </action>
</keymap>